frametree/xnat/__init__.py
frametree/xnat/_version.py
frametree/xnat/api.py
frametree/xnat/cs.py
frametree/xnat/testing.py
frametree/xnat/tests/test_store.py
frametree_xnat-0.6.14.dist-info/METADATA
frametree_xnat-0.6.14.dist-info/WHEEL
frametree_xnat-0.6.14.dist-info/licenses/LICENSE
frametree_xnat-0.6.14.dist-info/RECORD
